propeller_design_tools/__init__.py
propeller_design_tools/airfoil.py
propeller_design_tools/custom_opengl_classes.py
propeller_design_tools/foil_ui_classes.py
propeller_design_tools/funcs.py
propeller_design_tools/helper_ui_classes.py
propeller_design_tools/helper_ui_subclasses.py
propeller_design_tools/mobapp.py
propeller_design_tools/opt_ui_classes.py
propeller_design_tools/optimizations.py
propeller_design_tools/prop_analysis_ui_classes.py
propeller_design_tools/prop_creation_ui_classes.py
propeller_design_tools/propeller.py
propeller_design_tools/radialstation.py
propeller_design_tools/science_spinbox_class.py
propeller_design_tools/settings.py
propeller_design_tools/user_interface.py
propeller_design_tools/user_io.py
propeller_design_tools/foil_database/arad13.dat
propeller_design_tools/foil_database/clarky.dat
propeller_design_tools/foil_database/e855.dat
propeller_design_tools/foil_database/hs1606.dat
propeller_design_tools/foil_database/mrc-16.dat
propeller_design_tools/foil_database/xfoil.exe
propeller_design_tools/prop_database/xrotor.exe
propeller_design_tools/prop_database/MyPropeller/MyPropeller.meta
propeller_design_tools/prop_database/MyPropeller/MyPropeller.xrop
propeller_design_tools/prop_database/MyPropeller/MyPropeller.xrr
propeller_design_tools/prop_database/MyPropeller/blade_profiles/profile_0.txt
propeller_design_tools/prop_database/MyPropeller/blade_profiles/profile_1.txt
propeller_design_tools/prop_database/MyPropeller/blade_profiles/profile_10.txt
propeller_design_tools/prop_database/MyPropeller/blade_profiles/profile_11.txt
propeller_design_tools/prop_database/MyPropeller/blade_profiles/profile_12.txt
propeller_design_tools/prop_database/MyPropeller/blade_profiles/profile_13.txt
propeller_design_tools/prop_database/MyPropeller/blade_profiles/profile_14.txt
propeller_design_tools/prop_database/MyPropeller/blade_profiles/profile_15.txt
propeller_design_tools/prop_database/MyPropeller/blade_profiles/profile_16.txt
propeller_design_tools-0.4.7.dist-info/LICENSE
propeller_design_tools-0.4.7.dist-info/METADATA
propeller_design_tools-0.4.7.dist-info/WHEEL
propeller_design_tools-0.4.7.dist-info/top_level.txt
propeller_design_tools-0.4.7.dist-info/RECORD
