Metadata-Version: 2.1
Name: propeller-design-tools
Version: 0.4.7
Summary: Python 3.7 package that provides exactly what it sounds like by automating usage of MIT professor Mark Drela's GNU-licensed CLI-utilities XFOIL and XROTOR.
Author-email: Jacob Bronson <bronsoneering@gmail.com>
License: GNU GENERAL PUBLIC LICENSE
Project-URL: Homepage, https://github.com/helloDestroyerOfWorlds/propeller_design_tools.git
Project-URL: Documentation, https://github.com/helloDestroyerOfWorlds/propeller_design_tools.git
Project-URL: Repository, https://github.com/helloDestroyerOfWorlds/propeller_design_tools.git
Project-URL: Changelog, https://github.com/helloDestroyerOfWorlds/propeller_design_tools.git
Keywords: propeller,design,tools,computational,fluid,dynamics,CFD,STL,prop,rotor,xrotor,xfoil,MIT,Drela,Youngren,engineering,aero,dynamic,aerodynamic,hydrodynamic
Classifier: Intended Audience :: Science/Research
Classifier: License :: OSI Approved :: GNU General Public License v3 (GPLv3)
Classifier: Natural Language :: English
Classifier: Programming Language :: Python :: 3
Classifier: Operating System :: Microsoft :: Windows
Classifier: Operating System :: POSIX :: Linux
Classifier: Topic :: Scientific/Engineering
Classifier: Development Status :: 3 - Alpha
Requires-Python: >=3.7
License-File: LICENSE
Requires-Dist: numpy (>=1.21.2)
Requires-Dist: matplotlib (>=3.4.3)
Requires-Dist: scipy (>=1.7.1)
Requires-Dist: pyqtgraph (>=0.12.4)
Requires-Dist: pyopengl (>=3.1.6)
Requires-Dist: numpy-stl (>=2.16.3)
Provides-Extra: gui
Requires-Dist: PyQt5 (>=5.15.9) ; extra == 'gui'
